pyfmpcloud
