Metadata-Version: 2.1
Name: pyfmpcloud
Version: 1.1.5
Summary: A python-based wrapper for the Financial Models Prep pro API (fmpcloud.io) for financial data of public companies
Home-page: https://github.com/razorhash/pyfmpcloud/
Author: razorhash
Author-email: hashim.mazhar@gmail.com
License: MIT
Download-URL: https://github.com/razorhash/pyfmpcloud/archive/v1.1.5.tar.gz
Keywords: Financial Models Prep,python,wrapper,API,fmpcloud.io,fmpcloud
Platform: UNKNOWN
Classifier: Development Status :: 5 - Production/Stable
Classifier: Programming Language :: Python :: 3
Classifier: License :: OSI Approved :: MIT License
Classifier: Operating System :: OS Independent
Classifier: Intended Audience :: Financial and Insurance Industry
Requires-Python: >=3.6
